pyTempico/__init__.py
pyTempico/core.py
pyTempico/tempCodeRunnerFile.py
pyTempico/testFunctions.py
pyTempico/updateVersion.py
pytempico-2.0.1.dist-info/LICENSE
pytempico-2.0.1.dist-info/METADATA
pytempico-2.0.1.dist-info/WHEEL
pytempico-2.0.1.dist-info/top_level.txt
pytempico-2.0.1.dist-info/RECORD
