Metadata-Version: 2.1
Name: pyTempico
Version: 2.0.1
Summary: Built to use with Tausand Tempico time-to-digital converters
Home-page: https://github.com/Tausand-dev/PyTempico
Author: David Guzman
Author-email: da.guzman@outlook.com
Maintainer: David Guzman
Maintainer-email: da.guzman@outlook.com
License: GPL-3.0
Project-URL: Bug Tracker, https://github.com/Tausand-dev/PyTempico/issues
Classifier: Development Status :: 5 - Production/Stable
Classifier: Topic :: Utilities
Classifier: License :: OSI Approved :: GNU General Public License v3 (GPLv3)
Classifier: Operating System :: OS Independent
Classifier: Programming Language :: Python :: 3
Requires-Python: >=3.6
License-File: LICENSE
Requires-Dist: hidapi>=0.14.0
Requires-Dist: pyserial>=3.5
